polycirc/__init__.py
polycirc/ast.py
polycirc/decompose.py
polycirc/ir.py
polycirc/learner.py
polycirc/operation.py
polycirc/optic.py
polycirc/permutation.py
yarrow_polycirc-0.0.0.1.dist-info/METADATA
yarrow_polycirc-0.0.0.1.dist-info/WHEEL
yarrow_polycirc-0.0.0.1.dist-info/RECORD
