Metadata-Version: 2.1
Name: yarrow-polycirc
Version: 0.0.0.1
Summary: Differentiable IR for Zero-Knowledge Machine Learning
Project-URL: Homepage, https://github.com/yarrow-id/polycirc
Project-URL: Github, https://github.com/yarrow-id/polycirc
Author-email: Paul Wilson <paul@statusfailed.com>
Classifier: License :: OSI Approved :: GNU Affero General Public License v3
Classifier: Programming Language :: Python :: 3
Requires-Python: >=3.8
Requires-Dist: numpy~=1.21
Requires-Dist: yarrow-diagrams==0.0.3.1
Provides-Extra: dev
Requires-Dist: hypothesis; extra == 'dev'
Requires-Dist: pytest; extra == 'dev'
Provides-Extra: example
Requires-Dist: pandas; extra == 'example'
